{"FullPath":"C:\\Users\\samu-\\.nuget\\packages\\microsoft.winui\\3.0.0-preview3.201113.0\\lib\\uap10.0\\Microsoft.Graphics.winmd","InProcServers":{},"Namespaces":{"Microsoft.Graphics.IGeometrySource2D":"Microsoft.Graphics","Microsoft.Graphics.DirectX.DirectXColorSpace":"Microsoft.Graphics.DirectX","Microsoft.Graphics.DirectX.DirectXPixelFormat":"Microsoft.Graphics.DirectX","Microsoft.Graphics.DirectX.DirectXPrimitiveTopology":"Microsoft.Graphics.DirectX","Microsoft.Graphics.DirectX.DirectXAlphaMode":"Microsoft.Graphics.DirectX"},"RootNamespace":"Microsoft.Graphics","AssemblyVersion":"16.0.30804.86"}